bba_data_push/__init__.py
bba_data_push/bba_dataset_push.py
bba_data_push/commons.py
bba_data_push/constants.py
bba_data_push/logging.py
bba_data_push/push_atlas_release.py
bba_data_push/push_brainmesh.py
bba_data_push/push_cellComposition.py
bba_data_push/push_nrrd_volumetricdatalayer.py
tests/__init__.py
tests/conftest.py
tests/test_cli.py
tests/test_commons.py
tests/test_push_atlasrelease.py
tests/test_push_cellcomposition.py
tests/test_push_mesh.py
tests/test_push_volumetric.py
tests/test_forge_config/test_forge_config_demo.yaml
tests/test_forge_config/configuration/demo-resolver/entity-to-resource-mapping.hjson
tests/test_forge_config/configuration/demo-resolver/term-to-resource-mapping.hjson
tests/test_forge_config/configuration/demo-store/file-to-resource-mapping.hjson
tests/test_forge_config/data/demo-model/namespaces.json
tests/test_forge_config/data/demo-model/schemas.json
tests/test_forge_config/data/demo-model/vocabulary.json
tests/test_forge_config/data/demo-model/mappings/allen-cell-types-database/DictionaryMapping/NeuronMorphology.hjson
tests/test_forge_config/data/demo-model/mappings/allen-cell-types-database/DictionaryMapping/PatchedCell.hjson
tests/test_forge_config/data/demo-model/mappings/allen-cell-types-database/DictionaryMapping/Subject.hjson
tests/test_forge_config/data/demo-model/mappings/scientists-database/DictionaryMapping/Association.hjson
tests/test_forge_config/data/demo-resolver/agents.json
tests/test_forge_config/data/demo-resolver/sex.json
tests/test_forge_config/data/demo-resolver/species.json
tests/test_forge_config/data/demo-resolver/structure_layer.json
tests/test_forge_config/wrong_config/test_forge_config_demo.yaml
tests/tests_data/L1_NGC-SA.nrrd
tests/tests_data/L1_NGC-SA|cNAC.nrrd
tests/tests_data/annotation.nrrd
tests/tests_data/annotation_hybrid_l23split.nrrd
tests/tests_data/annotation_v2v3_hybrid.nrrd
tests/tests_data/atlasrelease_config_path.json
tests/tests_data/brain_region_mask_ccfv3_l23split.nrrd
blue_brain_data_push-5.0.0.dist-info/AUTHORS.txt
blue_brain_data_push-5.0.0.dist-info/LICENSE.txt
blue_brain_data_push-5.0.0.dist-info/METADATA
blue_brain_data_push-5.0.0.dist-info/WHEEL
blue_brain_data_push-5.0.0.dist-info/entry_points.txt
blue_brain_data_push-5.0.0.dist-info/top_level.txt
blue_brain_data_push-5.0.0.dist-info/RECORD
