Metadata-Version: 2.1
Name: blue_brain_data_push
Version: 5.0.0
Summary: Package creating resource payloads from atlas datasets and push them along with the corresponding dataset files into Nexus.
Home-page: https://github.com/BlueBrain/bbp-data-push
Author: Blue Brain Project, EPFL
License: Apache-2.0
Requires-Python: >=3.9
License-File: LICENSE.txt
License-File: AUTHORS.txt
Requires-Dist: nexusforge >=0.8.2
Requires-Dist: click >=7.0
Requires-Dist: numpy >=1.19
Requires-Dist: h5py >=2.10.0
Requires-Dist: pynrrd >=0.4.0
Requires-Dist: PyYAML >=5.3.1
Requires-Dist: PyJWT >=2.0.0
Requires-Dist: rdflib >=6.2.0
Requires-Dist: urllib3
Requires-Dist: voxcell
Provides-Extra: dev
Requires-Dist: pytest >=7.0.1 ; extra == 'dev'
Requires-Dist: pytest-cov >=2.8.0 ; extra == 'dev'
